itch_majordomo/__init__.py
itch_majordomo/itch_majordomo.py
itch_majordomo-0.1.0.dist-info/LICENSE
itch_majordomo-0.1.0.dist-info/METADATA
itch_majordomo-0.1.0.dist-info/WHEEL
itch_majordomo-0.1.0.dist-info/RECORD
