Metadata-Version: 2.1
Name: itch-majordomo
Version: 0.1.0
Summary: Automation tools for itch.io game management
Home-page: https://github.com/zorbathut/itch-majordomo
License: MIT
Author: Ben Rog-Wilhelm
Author-email: zorba-github@pavlovian.net
Requires-Python: >=3.12,<4.0
Classifier: License :: OSI Approved :: MIT License
Classifier: Programming Language :: Python :: 3
Classifier: Programming Language :: Python :: 3.12
Requires-Dist: selenium (>=4.26.1,<5.0.0)
Project-URL: Repository, https://github.com/zorbathut/itch-majordomo
